LICENSE
MANIFEST.in
README.md
requirements.txt
setup.py
dazzle/__init__.py
dazzle/dazzle.py
dazzle/wrap.py
dazzle.egg-info/PKG-INFO
dazzle.egg-info/SOURCES.txt
dazzle.egg-info/dependency_links.txt
dazzle.egg-info/requires.txt
dazzle.egg-info/top_level.txt