Metadata-Version: 1.1
Name: dazzle
Version: 1.0.1
Summary: Make your output sparkle, without long repetitive code
Home-page: https://github.com/Zwork101/Dazzle
Author: Nathan Zilora
Author-email: zwork101@gmail.com
License: MIT
Platform: UNKNOWN
Classifier: License :: OSI Approved :: MIT License
Classifier: Programming Language :: Python
Classifier: Programming Language :: Python :: 3
